{
    "coverage": {
        "US Census": {
            "geoid": "39151",
            "name": "Stark County",
            "state": "Ohio"
        },
        "country": "us",
        "state": "oh",
        "county": "Stark"
    },
    "schema": 2,
    "layers": {
        "addresses": [
            {
                "name": "country",
                "data": "http://data.openaddresses.io/runs/885649/us/oh/stark.zip",
                "protocol": "http",
                "compression": "zip",
                "conform": {
                    "format": "csv",
                    "lon": "LON",
                    "lat": "LAT",
                    "number": "NUMBER",
                    "street": "STREET",
                    "unit": "UNIT",
                    "city": "CITY",
                    "district": "DISTRICT",
                    "region": "REGION",
                    "postcode": "POSTCODE",
                    "id": "ID"
                }
            }
        ]
    }
}