{
    "coverage": {
        "US Census": {
            "geoid": "53009",
            "name": "Clallam County",
            "state": "Washington"
        },
        "country": "us",
        "state": "wa",
        "county": "Clallam"
    },
    "schema": 2,
    "layers": {
        "addresses": [
            {
                "name": "country",
                "conform": {
                    "format": "csv",
                    "lon": "LON",
                    "lat": "LAT",
                    "number": "NUMBER",
                    "street": "STREET",
                    "unit": "UNIT",
                    "city": "CITY",
                    "district": "DISTRICT",
                    "region": "REGION",
                    "postcode": "POSTCODE",
                    "id": "ID"
                },
                "license": "http://www.clallam.net/maps/parcels.html",
                "protocol": "http",
                "compression": "zip",
                "note": "parcel polygon shapefile prc_detail_p.shp, address columns: SITUS_ADDR, SITUS_DIR, SITUS_RD, SITUS_EXT, SITUS_CITY",
                "year": "2014",
                "data": "http://data.openaddresses.io/runs/885891/us/wa/clallam.zip",
                "website": "http://www.clallam.net/maps/mapdata.html"
            }
        ]
    }
}