{
    "coverage": {
        "geometry": {
            "type": "Point",
            "coordinates": [
                -100.837,
                46.809
            ]
        },
        "US Census": {
            "geoid": "3807200",
            "name": "City of Bismarck",
            "state": "North Dakota"
        },
        "country": "us",
        "state": "nd",
        "county": "Burleigh",
        "city": "Bismarck"
    },
    "schema": 2,
    "layers": {
        "addresses": [
            {
                "name": "country",
                "data": "http://data.openaddresses.io/runs/836930/us/nd/city_of_bismarck.zip",
                "protocol": "http",
                "conform": {
                    "format": "csv",
                    "lon": "LON",
                    "lat": "LAT",
                    "number": "NUMBER",
                    "street": "STREET",
                    "unit": "UNIT",
                    "city": "CITY",
                    "district": "DISTRICT",
                    "region": "REGION",
                    "postcode": "POSTCODE",
                    "id": "ID"
                },
                "compression": "zip"
            }
        ]
    }
}