{
    "coverage": {
        "country": "ca",
        "state": "on",
        "city": "Durham",
        "geometry": {
            "type": "Point",
            "coordinates": [
                -79.14,
                43.85
            ]
        }
    },
    "schema": 2,
    "layers": {
        "addresses": [
            {
                "name": "country",
                "data": "http://data.openaddresses.io/runs/885463/ca/on/township_of_durham.zip",
                "website": "https://www.durham.ca/corpservices.asp?nr=/departments/corpservices/it/gis/opendata.htm&setFooter=/includes/GISfooter.inc",
                "license": "https://www.durham.ca/corpservices.asp?nr=/departments/corpservices/it/gis/opendatalicense.htm&setFooter=/includes/GISfooter.inc",
                "protocol": "http",
                "conform": {
                    "format": "csv",
                    "lon": "LON",
                    "lat": "LAT",
                    "number": "NUMBER",
                    "street": "STREET",
                    "unit": "UNIT",
                    "city": "CITY",
                    "district": "DISTRICT",
                    "region": "REGION",
                    "postcode": "POSTCODE",
                    "id": "ID"
                },
                "compression": "zip"
            }
        ]
    }
}