{
    "coverage": {
        "US Census": {
            "geoid": "55105",
            "name": "Rock County",
            "state": "Wisconsin"
        },
        "country": "us",
        "state": "wi",
        "county": "Rock"
    },
    "schema": 2,
    "layers": {
        "addresses": [
            {
                "name": "country",
                "data": "http://data.openaddresses.io/runs/618661/us/wi/rock.zip",
                "protocol": "http",
                "conform": {
                    "format": "csv",
                    "lon": "LON",
                    "lat": "LAT",
                    "number": "NUMBER",
                    "street": "STREET",
                    "unit": "UNIT",
                    "city": "CITY",
                    "district": "DISTRICT",
                    "region": "REGION",
                    "postcode": "POSTCODE",
                    "id": "ID"
                },
                "compression": "zip"
            }
        ]
    }
}