{
    "coverage": {
        "US Census": {
            "geoid": "24027",
            "name": "Howard County",
            "state": "Maryland"
        },
        "country": "us",
        "state": "md",
        "county": "Howard"
    },
    "schema": 2,
    "layers": {
        "addresses": [
            {
                "name": "country",
                "data": "http://data.openaddresses.io/runs/886099/us/md/howard.zip",
                "website": "http://data.howardcountymd.gov/",
                "license": {
                    "text": "PD",
                    "attribution": false,
                    "share-alike": false
                },
                "compression": "zip",
                "protocol": "http",
                "year": 2013,
                "conform": {
                    "format": "csv",
                    "lon": "LON",
                    "lat": "LAT",
                    "number": "NUMBER",
                    "street": "STREET",
                    "unit": "UNIT",
                    "city": "CITY",
                    "district": "DISTRICT",
                    "region": "REGION",
                    "postcode": "POSTCODE",
                    "id": "ID"
                }
            }
        ]
    }
}