{
    "coverage": {
        "US Census": {
            "geoid": "12045",
            "name": "Gulf County",
            "state": "Florida"
        },
        "country": "us",
        "state": "fl",
        "county": "Gulf"
    },
    "schema": 2,
    "layers": {
        "addresses": [
            {
                "name": "country",
                "conform": {
                    "format": "csv",
                    "lon": "LON",
                    "lat": "LAT",
                    "number": "NUMBER",
                    "street": "STREET",
                    "unit": "UNIT",
                    "city": "CITY",
                    "district": "DISTRICT",
                    "region": "REGION",
                    "postcode": "POSTCODE",
                    "id": "ID"
                },
                "data": "http://data.openaddresses.io/runs/837483/us/fl/gulf.zip",
                "protocol": "http",
                "website": "http://maps2.roktech.net/GulfGoMaps4/?mapName=GIS",
                "compression": "zip"
            }
        ]
    }
}