{
    "coverage": {
        "country": "ca",
        "state": "ab",
        "city": "Banff",
        "geometry": {
            "type": "Point",
            "coordinates": [
                -115.57,
                51.18
            ]
        }
    },
    "schema": 2,
    "layers": {
        "addresses": [
            {
                "name": "country",
                "data": "http://data.openaddresses.io/runs/886903/ca/ab/city_of_banff.zip",
                "website": "http://www.banffopendata.ca/DataBrowser/BanffData/AddressPoints",
                "license": "http://www.banffopendata.ca/Home/About",
                "protocol": "http",
                "compression": "zip",
                "attribution": "City of Banff",
                "conform": {
                    "format": "csv",
                    "lon": "LON",
                    "lat": "LAT",
                    "number": "NUMBER",
                    "street": "STREET",
                    "unit": "UNIT",
                    "city": "CITY",
                    "district": "DISTRICT",
                    "region": "REGION",
                    "postcode": "POSTCODE",
                    "id": "ID"
                }
            }
        ]
    }
}