{
    "coverage": {
        "ISO 3166": {
            "alpha2": "KR-28",
            "country": "Republic of Korea",
            "subdivision": "Incheon"
        },
        "country": "kr",
        "state": "28"
    },
    "schema": 2,
    "layers": {
        "addresses": [
            {
                "name": "country",
                "data": "http://data.openaddresses.io/runs/885549/kr/28/provincewide.zip",
                "website": "http://www.juso.go.kr/addrlink/addressBuildDevNew.do?menu=geodata",
                "license": {
                    "attribution name": "Ministry of the Interior"
                },
                "protocol": "http",
                "compression": "zip",
                "language": "kr",
                "conform": {
                    "format": "csv",
                    "lon": "LON",
                    "lat": "LAT",
                    "number": "NUMBER",
                    "street": "STREET",
                    "unit": "UNIT",
                    "city": "CITY",
                    "district": "DISTRICT",
                    "region": "REGION",
                    "postcode": "POSTCODE",
                    "id": "ID"
                }
            }
        ]
    }
}