{
    "coverage": {
        "US Census": {
            "geoid": "27037",
            "name": "Dakota County",
            "state": "Minnesota"
        },
        "country": "us",
        "state": "mn",
        "county": "Dakota"
    },
    "schema": 2,
    "layers": {
        "addresses": [
            {
                "name": "country",
                "license": "https://www.co.dakota.mn.us/HomeProperty/MappingServices/GISData/Pages/default.aspx",
                "protocol": "http",
                "note": "ArcGIS for Server service",
                "data": "http://data.openaddresses.io/runs/885385/us/mn/dakota.zip",
                "website": "http://www.co.dakota.mn.us/HomeProperty/MappingServices/GISData/Pages/default.aspx",
                "conform": {
                    "format": "csv",
                    "lon": "LON",
                    "lat": "LAT",
                    "number": "NUMBER",
                    "street": "STREET",
                    "unit": "UNIT",
                    "city": "CITY",
                    "district": "DISTRICT",
                    "region": "REGION",
                    "postcode": "POSTCODE",
                    "id": "ID"
                },
                "compression": "zip"
            }
        ]
    }
}