{
    "coverage": {
        "US Census": {
            "geoid": "27139",
            "name": "Scott County",
            "state": "Minnesota"
        },
        "country": "us",
        "state": "mn",
        "county": "Scott"
    },
    "schema": 2,
    "layers": {
        "addresses": [
            {
                "name": "country",
                "protocol": "http",
                "data": "http://data.openaddresses.io/runs/885912/us/mn/scott.zip",
                "website": "http://opendata.gis.co.scott.mn.us/datasets/69c050b1159540c29c7ffc884c12f066_0",
                "conform": {
                    "format": "csv",
                    "lon": "LON",
                    "lat": "LAT",
                    "number": "NUMBER",
                    "street": "STREET",
                    "unit": "UNIT",
                    "city": "CITY",
                    "district": "DISTRICT",
                    "region": "REGION",
                    "postcode": "POSTCODE",
                    "id": "ID"
                },
                "compression": "zip"
            }
        ]
    }
}